MANIFEST.in
setup.py
forest/forest.xls
src/icc/__init__.py
src/icc.atp.egg-info/PKG-INFO
src/icc.atp.egg-info/SOURCES.txt
src/icc.atp.egg-info/dependency_links.txt
src/icc.atp.egg-info/namespace_packages.txt
src/icc.atp.egg-info/requires.txt
src/icc.atp.egg-info/top_level.txt
src/icc.atp.egg-info/zip-safe
src/icc/atp/src/atp.d